flask_xinidea/__init__.py
flask_xinidea/redprint.py
flask_xinidea/reflectdb.py
flask_xinidea-0.0.4.dist-info/LICENSE
flask_xinidea-0.0.4.dist-info/METADATA
flask_xinidea-0.0.4.dist-info/WHEEL
flask_xinidea-0.0.4.dist-info/top_level.txt
flask_xinidea-0.0.4.dist-info/RECORD
