Metadata-Version: 2.1
Name: flask-xinidea
Version: 0.0.4
Summary: Some Flask custom extension
Home-page: UNKNOWN
Author: phiix
Author-email: phiix@qq.com
License: UNKNOWN
Platform: UNKNOWN
Classifier: Programming Language :: Python :: 3
Classifier: License :: OSI Approved :: MIT License
Classifier: Operating System :: OS Independent
Requires-Python: >=3.6
